progresstools/__init__.py
progresstools/progress.py
progresstools-1.0.0.dist-info/licenses/LICENSE
progresstools-1.0.0.dist-info/METADATA
progresstools-1.0.0.dist-info/WHEEL
progresstools-1.0.0.dist-info/top_level.txt
progresstools-1.0.0.dist-info/RECORD
