Metadata-Version: 2.4
Name: progresstools
Version: 1.0.0
Summary: Simple progress bar utilities for Python CLI use.
Author: Unknown
License: MIT License
Project-URL: Homepage, https://pypi.org/project/progresstools/
Requires-Python: >=3.6
License-File: LICENSE
Dynamic: author
Dynamic: license-file
